<?xml version="1.0" encoding="UTF-8"?>
<con:soapui-project id="9a9f0395-cd3e-4961-bd80-da042ff6014f" activeEnvironment="Default" name="RESTAssertionXML" resourceRoot="" soapui-version="5.6.0" xmlns:con="http://eviware.com/soapui/config"><con:settings/><con:interface xsi:type="con:RestService" id="2db8ff6c-0f52-41b8-beb6-15e5cda8a282" wadlVersion="http://wadl.dev.java.net/2009/02" name="https://maps.googleapis.com" type="rest" xmlns:xsi="http://www.w3.org/2001/XMLSchema-instance"><con:settings/><con:definitionCache/><con:endpoints><con:endpoint>https://maps.googleapis.com</con:endpoint></con:endpoints><con:resource name="Xml" path="/maps/api/place/textsearch/xml" id="e01be764-b485-4d6a-bd2b-6e48eab7ee3a"><con:settings/><con:parameters><con:parameter><con:name>query</con:name><con:value>restaurants in Sydney</con:value><con:style>QUERY</con:style><con:default>restaurants in Sydney</con:default><con:path xsi:nil="true"/><con:description xsi:nil="true"/></con:parameter><con:parameter><con:name>key</con:name><con:value>YOUR_API_KEY</con:value><con:style>QUERY</con:style><con:default>YOUR_API_KEY</con:default><con:path xsi:nil="true"/><con:description xsi:nil="true"/></con:parameter></con:parameters><con:method name="Xml 1" id="d88e9b69-ead4-422e-ab40-650cb57ed09f" method="GET"><con:settings/><con:parameters/><con:request name="Request 1" id="12fe845a-7b14-4126-b4f7-6707976b951c" mediaType="application/json"><con:settings/><con:endpoint>https://maps.googleapis.com</con:endpoint><con:request/><con:credentials><con:authType>No Authorization</con:authType></con:credentials><con:jmsConfig JMSDeliveryMode="PERSISTENT"/><con:jmsPropertyConfig/><con:parameters>
  <con:entry key="query" value="restaurants in Sydney"/>
  <con:entry key="key" value="YOUR_API_KEY"/>
</con:parameters><con:parameterOrder><con:entry>query</con:entry><con:entry>key</con:entry></con:parameterOrder></con:request></con:method></con:resource></con:interface><con:properties/><con:wssContainer/><con:oAuth2ProfileContainer/><con:oAuth1ProfileContainer/><con:sensitiveInformation/></con:soapui-project>